__init__.py
config.py
connection.py
main.py
server.py
mseep_mcp_server_redis-0.1.4.dist-info/licenses/LICENSE
resources/__init__.py
resources/keys.py
resources/status.py
tools/__init__.py
tools/basic.py
tools/hashes.py
tools/lists.py
tools/pubsub.py
tools/sets.py
mseep_mcp_server_redis-0.1.4.dist-info/METADATA
mseep_mcp_server_redis-0.1.4.dist-info/WHEEL
mseep_mcp_server_redis-0.1.4.dist-info/top_level.txt
mseep_mcp_server_redis-0.1.4.dist-info/RECORD
