Metadata-Version: 2.4
Name: mseep-mcp-server-redis
Version: 0.1.4
Summary: MCP server to interact with redis server, aws memory DB, etc for caching or other use-cases where in-memory and key-value based storage is appropriate
Author-email: mseep <support@skydeck.ai>
Requires-Python: >=3.13
License-File: LICENSE
Requires-Dist: mcp[cli]>=1.2.1
Requires-Dist: python-dotenv>=1.0.1
Requires-Dist: redis>=5.2.1
Dynamic: license-file
